demos/basic_usage.py
demos/before_after_comparison.py
docs/conf.py
paper_voice/__init__.py
paper_voice/arxiv_downloader.py
paper_voice/cli.py
paper_voice/content_processor.py
paper_voice/document_processor.py
paper_voice/figure_table_summarizer.py
paper_voice/latex_processor.py
paper_voice/natural_math_speech.py
paper_voice/pdf_content_enhancer.py
paper_voice/pdf_extractor.py
paper_voice/pdf_utils.py
paper_voice/selective_enhancer.py
paper_voice/simple_llm_enhancer.py
paper_voice/tts.py
paper_voice/vision_pdf_analyzer.py
streamlit/app.py
tests/simple_latex_test.py
tests/test_arxiv_downloader.py
tests/test_batch_processing.py
tests/test_enhanced.py
tests/test_latex_enhancement.py
tests/test_latex_processor.py
tests/test_runner.py
tests/test_selective_enhancement.py
tests/test_tts_chunking.py
tests/test_vision_analyzer.py
paper_voice-0.3.0.dist-info/METADATA
paper_voice-0.3.0.dist-info/WHEEL
paper_voice-0.3.0.dist-info/entry_points.txt
paper_voice-0.3.0.dist-info/top_level.txt
paper_voice-0.3.0.dist-info/RECORD
