Metadata-Version: 2.4
Name: paper_voice
Version: 0.3.0
Summary: Convert academic papers to high-quality audio with precise mathematical explanations and intelligent content processing
Author-email: Gaurav Sood <gsood07@gmail.com>
Project-URL: homepage, https://github.com/gojiplus/paper_voice
Project-URL: repository, https://github.com/gojiplus/paper_voice
Project-URL: documentation, https://gojiplus.github.io/paper_voice
Requires-Python: !=3.9.7,>=3.9
Requires-Dist: streamlit>=1.30.0
Requires-Dist: PyPDF2>=3.0.1
Requires-Dist: pyttsx3>=2.90
Requires-Dist: regex>=2024.2.2
Requires-Dist: pydub>=0.25.1
Requires-Dist: openai>=1.0.0
Requires-Dist: PyMuPDF>=1.23.0
Requires-Dist: requests>=2.31.0
Provides-Extra: test
Requires-Dist: pytest>=7.0.0; extra == "test"
Requires-Dist: pytest-cov>=4.0.0; extra == "test"
Requires-Dist: pytest-mock>=3.10.0; extra == "test"
Provides-Extra: dev
Requires-Dist: pytest>=7.0.0; extra == "dev"
Requires-Dist: pytest-cov>=4.0.0; extra == "dev"
Requires-Dist: pytest-mock>=3.10.0; extra == "dev"
Requires-Dist: black>=23.0.0; extra == "dev"
Requires-Dist: flake8>=6.0.0; extra == "dev"
Requires-Dist: mypy>=1.0.0; extra == "dev"
